petrolib/__init__.py
petrolib/file_reader.py
petrolib/interp.py
petrolib/plots.py
petrolib/procs.py
petrolib/stats.py
petrolib/utils.py
petrolib/workflow.py
petrolib/data/litho_info.csv
petrolib-1.2.6.dist-info/LICENSE
petrolib-1.2.6.dist-info/METADATA
petrolib-1.2.6.dist-info/WHEEL
petrolib-1.2.6.dist-info/top_level.txt
petrolib-1.2.6.dist-info/RECORD
