Metadata-Version: 2.1
Name: petrolib
Version: 1.2.6
Summary: A Python Package for Petrophysical Evaluation
Author-email: Joshua Atolagbe <atolagbejoshua2@gmail.com>
Project-URL: Homepage, https://github.com/joshua-atolagbe/petrolib
Project-URL: Bug Tracker, https://github.com/joshua-atolagbe/petrolib/issues
Classifier: Programming Language :: Python :: 3
Classifier: License :: OSI Approved :: MIT License
Classifier: Operating System :: OS Independent
Requires-Python: >=3.7
License-File: LICENSE
Requires-Dist: matplotlib
Requires-Dist: pandas
Requires-Dist: numpy
Requires-Dist: lasio
Requires-Dist: scipy
Requires-Dist: seaborn
Requires-Dist: geopandas
Requires-Dist: contextily
